gcputil/__init__.py
gcputil/gcputil.py
gcputil-0.1.0.dist-info/LICENSE.txt
gcputil-0.1.0.dist-info/METADATA
gcputil-0.1.0.dist-info/WHEEL
gcputil-0.1.0.dist-info/top_level.txt
gcputil-0.1.0.dist-info/RECORD
