Metadata-Version: 2.1
Name: gcputil
Version: 0.1.0
Summary: A package to use gcp functions
Home-page: UNKNOWN
Author: Travis Kirton
Author-email: traviskirton@outlook.com
License: UNKNOWN
Platform: UNKNOWN
Classifier: Programming Language :: Python :: 3
Classifier: License :: OSI Approved :: MIT License
Classifier: Operating System :: OS Independent
